odoo/addons/donation_sale/README.rst
odoo/addons/donation_sale/__init__.py
odoo/addons/donation_sale/__manifest__.py
odoo/addons/donation_sale/data/cron.xml
odoo/addons/donation_sale/i18n/de.po
odoo/addons/donation_sale/i18n/donation_sale.pot
odoo/addons/donation_sale/i18n/fr.po
odoo/addons/donation_sale/models/__init__.py
odoo/addons/donation_sale/models/account_invoice.py
odoo/addons/donation_sale/models/donation_sale.py
odoo/addons/donation_sale/models/sale.py
odoo/addons/donation_sale/static/description/icon.png
odoo/addons/donation_sale/tests/__init__.py
odoo/addons/donation_sale/tests/test_donation_sale.py
odoo/addons/donation_sale/views/account_invoice.xml
odoo/addons/donation_sale/views/donation_tax.xml
odoo/addons/donation_sale/views/sale_order.xml
odoo11_addon_donation_sale-11.0.1.0.0.99.dev10.dist-info/METADATA
odoo11_addon_donation_sale-11.0.1.0.0.99.dev10.dist-info/WHEEL
odoo11_addon_donation_sale-11.0.1.0.0.99.dev10.dist-info/top_level.txt
odoo11_addon_donation_sale-11.0.1.0.0.99.dev10.dist-info/RECORD
